riverreliability/__init__.py
riverreliability/_nbdev.py
riverreliability/beta.py
riverreliability/metrics.py
riverreliability/plots.py
riverreliability/utils.py
riverreliability-0.1.2.dist-info/LICENSE
riverreliability-0.1.2.dist-info/METADATA
riverreliability-0.1.2.dist-info/WHEEL
riverreliability-0.1.2.dist-info/entry_points.txt
riverreliability-0.1.2.dist-info/top_level.txt
riverreliability-0.1.2.dist-info/RECORD
