Metadata-Version: 2.1
Name: riverreliability
Version: 0.1.2
Summary: The river reliability diagram provides insight into classifier calibration with a visualization and metric based on the posterior balanaced accuracy.
Home-page: https://github.com/MaximLippeveld/riverreliability/tree/master/
Author: Maxim Lippeveld & Jonathan Peck
Author-email: maxim.lippeveld@ugent.be
License: Apache Software License 2.0
Keywords: reliability,confidence,classification,visualization,metric
Platform: UNKNOWN
Classifier: Development Status :: 5 - Production/Stable
Classifier: Intended Audience :: Developers
Classifier: License :: OSI Approved :: Apache Software License
Classifier: Natural Language :: English
Classifier: Programming Language :: Python :: 3.6
Classifier: Programming Language :: Python :: 3.7
Classifier: Programming Language :: Python :: 3.8
Requires-Python: >=3.6
Requires-Dist: matplotlib
Requires-Dist: numpy
Requires-Dist: scipy
Requires-Dist: pandas
Requires-Dist: sklearn
